{
  "navigation": {
    "logo": "أوربانس",
    "links": [
      { "label": "خدماتنا", "href": "#services" },
      { "label": "من نحن", "href": "#about" },
      { "label": "نتائجنا", "href": "#results" },
      { "label": "تواصل معنا", "href": "#contact" }
    ],
    "cta": "ابدأ معنا"
  },
  "hero": {
    "headline": {
      "primary": "توقف عن التعامل مع 12 مورد مختلف.",
      "secondary": "ابدأ في تنمية أعمالك مع أورباناس."
    },
    "subheadline": "الشريك السعودي الوحيد الذي يقدم امتثال أرامكو، والهجرة السحابية، والأمن السيبراني تحت سقف واحد",
    "hook": "من فوضى الامتثال إلى التميز الرقمي - في شراكة واحدة",
    "cta": {
      "primary": "احصل على تقييم مجاني",
      "secondary": "استكشف حلولنا"
    },
    "badges": [
      "12 قسم تحت سقف واحد",
      "معتمد ISO ومعتمد من أرامكو", 
      "دعم سعودي على مدار الساعة"
    ]
  },
  "about": {
    "title": "نحن لا نعمل في السعودية فقط - نحن السعودية",
    "subtitle": "بينما تفشل الشركات الدولية هنا، نحن ننجح لأننا نفهم طريقة العمل السعودية",
    "description": "كل مدير تنفيذي سعودي يواجه نفس الكابوس, إدارة موردين متعددين لا يستطيعون التنسيق، ويلومون بعضهم عند الفشل، ولا يفهمون اللوائح المحلية. أوربانس تحل هذه المشكلة بـ 12 قسم متكامل تحت سقف واحد.",
    "features": [
      {
        "title": "حل من مصدر واحد",
        "description": "شراكة واحدة لكل شيء من امتثال أرامكو إلى التحول الرقمي"
      },
      {
        "title": "خبرة في السوق السعودي", 
        "description": "فهم عميق للوائح المحلية والثقافة وممارسات الأعمال"
      },
      {
        "title": "تسليم متكامل",
        "description": "جميع الأقسام تعمل معاً - لا لوم، لا صداع في التنسيق"
      }
    ]
  },
  "services": {
    "title": "12 قسم، إمكانيات لا نهائية",
    "subtitle": "توقف عن لعبة الحظ مع الموردين. احصل على حلول متطورة عبر جميع وظائف الأعمال.",
    "grid": [
      {
        "id": "iso-compliance",
        "title": "حلول ISO والامتثال",
        "hook": "اربح عقود أرامكو بينما منافسوك ينتظرون الموافقات",
        "description": "تسريع اعتمادك، وفتح فرص أكبر",
        "services": ["أرامكو CCC/CCC+", "ISO 9001, 27001, 45001", "تحليل الفجوات", "دعم التدقيق"],
        "icon": "shield-check"
      },
      {
        "id": "cloud-microsoft",
        "title": "الحلول السحابية ومايكروسوفت",
        "hook": "مايكروسوفت بالطريقة الصحيحة - لا توقف، لا دراما",
        "description": "انتقال سلس يعزز الإنتاجية من اليوم الأول",
        "services": ["هجرة Microsoft 365", "بنية Azure التحتية", "خطوط DevOps", "دعم 24/7"],
        "icon": "cloud"
      },
      {
        "id": "erp-solutions",
        "title": "حلول ERP المؤسسية", 
        "hook": "ERP يسرع أعمالك فعلاً",
        "description": "أنظمة تعمل كما تفكر أعمالك",
        "services": ["Dynamics 365", "SAP Ariba", "Oracle Fusion", "التكامل المخصص"],
        "icon": "database"
      },
      {
        "id": "cybersecurity",
        "title": "حلول الأمن السيبراني",
        "hook": "نم مطمئناً - القراصنة السعوديون لا يستطيعون لمسك",
        "description": "حماية شاملة تحول فريقك إلى أقوى جدار حماية",
        "services": ["حماية نقاط النهاية", "أمن البريد الإلكتروني", "اختبار الاختراق", "تدريب الأمان"],
        "icon": "shield"
      },
      {
        "id": "network-infrastructure",
        "title": "الشبكات والبنية التحتية",
        "hook": "بنية تحتية موثوقة جداً، ستنسى وجودها", 
        "description": "مبنية للظروف السعودية، مصممة للنمو السعودي",
        "services": ["شبكات Cisco & Aruba", "مراكز البيانات", "أمان Fortinet", "أنظمة النسخ الاحتياطي"],
        "icon": "network"
      },
      {
        "id": "smart-security",
        "title": "الأمان الذكي والمراقبة",
        "hook": "راقب كل شيء، أمّن كل شيء، من أي مكان",
        "description": "مراقبة مدعومة بالذكاء الاصطناعي تتكامل مع اللوائح السعودية",
        "services": ["مراقبة CCTV و IP", "التحكم في الوصول", "أنظمة RFID", "التعرف على الوجه"],
        "icon": "camera"
      },
      {
        "id": "web-digital",
        "title": "خدمات الويب والرقمية",
        "hook": "حضور رقمي يحول العملاء السعوديين",
        "description": "مواقع ويب وحملات مصممة لسلوك المستهلك السعودي",
        "services": ["منصات التجارة الإلكترونية", "تطبيقات الجوال", "تحسين SEO", "وسائل التواصل الاجتماعي"],
        "icon": "globe"
      },
      {
        "id": "general-trading",
        "title": "التجارة العامة",
        "hook": "من أجهزة IT إلى المنتجات المميزة",
        "description": "مصادر عالمية، تسليم محلي بأسعار لا تقبل المنافسة",
        "services": ["معدات IT", "مستلزمات المكاتب", "منتجات FMCG", "الإلكترونيات الاستهلاكية"],
        "icon": "package"
      },
      {
        "id": "hr-manpower",
        "title": "الموارد البشرية وتوريد العمالة",
        "hook": "المواهب المناسبة، في الوقت المناسب",
        "description": "خبراء تقنيون مدروسون لمتطلبات السوق السعودي",
        "services": ["متخصصو IT", "عمالة ماهرة", "موظفو إداريون", "توظيف مؤقت"],
        "icon": "users"
      },
      {
        "id": "facility-support",
        "title": "المرافق والدعم المؤسسي",
        "hook": "ركز على النمو بينما نتولى كل شيء آخر",
        "description": "دعم تشغيلي كامل لراحة بالك",
        "services": ["إدارة المرافق", "التدريب المؤسسي", "اللوجستيات", "إدارة الفعاليات"],
        "icon": "building"
      },
      {
        "id": "marketing-branding",
        "title": "التسويق والعلامة التجارية",
        "hook": "هوية العلامة التجارية التي تتحدث السعودية بطلاقة",
        "description": "علامة تجارية ثنائية اللغة تتردد صداها مع الجماهير المحلية والدولية",
        "services": ["الهوية المؤسسية", "تطوير الشعار", "العروض التقديمية", "إنتاج الفيديو"],
        "icon": "paintbrush"
      }
    ]
  },
  "integration": {
    "title": "لماذا يختار عملاؤنا التكامل على فوضى الموردين",
    "subtitle": "ما يحدث عندما تعمل جميع الأقسام الـ 12 معاً لنجاحك",
    "story": {
      "challenge": "شركة تصنيع في الرياض احتاجت امتثال أرامكو، وتحديث ERP، والأمن السيبراني قبل موعد عقد حرج",
      "solution": "بينما طلب المنافسون 6 موردين و12 شهراً، حقق نهجنا المتكامل كل شيء في 4 أشهر",
      "result": "فازت بعقد أرامكو كبير، وقللت التكاليف بنسبة 35%، وحققت اعتماد ISO قبل الموعد المحدد"
    }
  },
  "stats": {
    "title": "أرقام تتحدث أعلى من الوعود",
    "subtitle": "نتائج حقيقية للشركات السعودية الحقيقية",
    "metrics": [
      {
        "value": "12+",
        "label": "قسم متكامل",
        "description": "كل شيء تحت سقف واحد"
      },
      {
        "value": "500+", 
        "label": "شركة سعودية تم خدمتها",
        "description": "عبر جميع المدن الرئيسية"
      },
      {
        "value": "99.9%",
        "label": "وقت تشغيل النظام",
        "description": "بنية تحتية موثوقة"
      },
      {
        "value": "24/7",
        "label": "دعم سعودي", 
        "description": "دائماً هنا عندما تحتاجنا"
      }
    ]
  },
  "cta": {
    "title": "مستعد للتوقف عن لعبة الحظ مع الموردين؟",
    "phoneNumber": "+966 57 616 3141",
    "subtitle": "احصل على تقييم مجاني لأعمالك",
    "hook": "في 30 دقيقة، سنوضح لك بالضبط كيفية حل أكبر 3 تحديات في أعمالك",
    "urgency": "محدود لـ 10 شركات سعودية شهرياً",
    "buttons": {
      "primary": "احجز تقييمك",
      "secondary": "اتصل الآن: +966 57 616 3141"
    },
    "guarantee": "إذا لم نتمكن من تحديد 3 طرق على الأقل لتحسين عملياتك، فالتقييم مجاني",
    "location": "مقر أوربانس، جدة - حيث تبدأ قصص النجاح السعودية"
  },
  "footer": {
    "tagline": "من الامتثال إلى السحابة، نبني قصص النجاح السعودية",
    "address": "جدة، المملكة العربية السعودية",
    "email": "hello@orbanas.sa",
    "divisions": [
      "ISO والامتثال",
      "الحلول السحابية", 
      "أنظمة ERP",
      "الأمن السيبراني",
      "البنية التحتية",
      "الأمان الذكي",
      "الويب والرقمية",
      "التجارة",
      "الموارد البشرية",
      "دعم المرافق",
      "التسويق"
    ]
  },
  "team": {
    "title": "تعرف على القادة وراء نجاح الأعمال السعودية",
    "subtitle": "العقول المبدعة التي تقود أوربانس نحو المستقبل", 
    "description": "يجمع فريق قيادتنا بين الخبرة العميقة في السوق السعودي والفطنة التجارية الدولية لتحقيق نتائج تحويلية لعملائنا.",
    "members": [
      {
        "id": "gm",
        "name": "محمد أنس",
        "position": "المدير العام",
        "department": "القيادة التنفيذية",
        "bio": "يقود أوربانس بخبرة تزيد عن 6 سنوات في التحول التجاري السعودي. متخصص في امتثال أرامكو والمبادرات الرقمية واسعة النطاق.",
        "expertise": ["التخطيط الاستراتيجي", "علاقات أرامكو", "تطوير الأعمال", "توسع السوق"],
        "image": "/team/gm.png",
        "linkedin": "https://linkedin.com/in/iamohammadanas",
        "achievements": "قاد أكثر من 200 مشروع امتثال ناجح بقيمة تزيد عن 500 مليون ريال"
      },
      {
        "id": "it-manager",
        "name": "توحيد الإسلام شايان", 
        "position": "مدير تقنية المعلومات",
        "department": "حلول التكنولوجيا",
        "bio": "يصمم حلول تقنية متطورة بخبرة تزيد عن 7 سنوات للمؤسسات الدولية. خبير في الهجرة السحابية والأمن السيبراني ونظام مايكروسوفت.",
        "expertise": ["العمارة السحابية", "الأمن السيبراني", "مايكروسوفت 365", "التحول الرقمي"],
        "image": "/team/it-manager.png", 
        "linkedin": "https://linkedin.com/in/chnspart",
        "achievements": "نقل أكثر من 15000 مستخدم إلى السحابة بوقت تشغيل 99.9%"
      }
    ]
  }
}